statstube/__init__.py
statstube/video.py
statstube-0.2.0.dist-info/LICENSE
statstube-0.2.0.dist-info/METADATA
statstube-0.2.0.dist-info/WHEEL
statstube-0.2.0.dist-info/top_level.txt
statstube-0.2.0.dist-info/RECORD
