Metadata-Version: 2.1
Name: statstube
Version: 0.2.0
Summary: This project aims to provide a proper and simpler way to crawl YouTube content.
Home-page: UNKNOWN
Author: William Kana
Author-email: UNKNOWN
License: Apache-2.0 License
Platform: UNKNOWN
